iam_mfa/__init__.py
iam_mfa/iam_mfa.py
iam_mfa-0.1.0.dist-info/licenses/LICENSE
iam_mfa-0.1.0.dist-info/METADATA
iam_mfa-0.1.0.dist-info/WHEEL
iam_mfa-0.1.0.dist-info/entry_points.txt
iam_mfa-0.1.0.dist-info/top_level.txt
iam_mfa-0.1.0.dist-info/RECORD
