Metadata-Version: 2.4
Name: iam-mfa
Version: 0.1.0
Summary: A command line tool to manage AWS CLI credentials with MFA (multi-factor authentication)
Author-email: "Zagaran, Inc." <info@zagaran.com>
License-Expression: MIT
Project-URL: Homepage, https://github.com/zagaran/iam-mfa
Keywords: aws,cli,iam,mfa
Classifier: Programming Language :: Python :: 3
Classifier: Operating System :: OS Independent
Requires-Python: >=3.6
License-File: LICENSE
Dynamic: license-file
